MANIFEST.in
README.markdown
setup.py
ciciol/__init__.py
ciciol/config.py
ciciol/helpers.py
ciciol.egg-info/PKG-INFO
ciciol.egg-info/SOURCES.txt
ciciol.egg-info/dependency_links.txt
ciciol.egg-info/requires.txt
ciciol.egg-info/top_level.txt
ciciol.egg-info/zip-safe
ciciol/backends/__init__.py
ciciol/backends/dummy.py
ciciol/backends/notify.py
ciciol/handlers/__init__.py
ciciol/handlers/dummy.py
ciciol/handlers/twitter.py
ciciol/utils/__init__.py
ciciol/utils/setup.py
scripts/ciciol