Metadata-Version: 1.0
Name: ciciol
Version: 0.1.1
Summary: Lightweight and extremely customizable notifier.  Designed to work with Twitter and much more
Home-page: http://github.com/volpino/Ciciol
Author: fox
Author-email: fox91 at anche no
License: BSD
Platform: UNKNOWN
Classifier: Development Status :: 3 - Alpha
Classifier: Environment :: Web Environment
Classifier: Intended Audience :: End Users/Desktop
Classifier: License :: OSI Approved :: BSD License
Classifier: Operating System :: OS Independent
Classifier: Programming Language :: Python
Classifier: Topic :: Utilities
